vibe_notification/__init__.py
vibe_notification/__main__.py
vibe_notification/adapters.py
vibe_notification/cli.py
vibe_notification/config.py
vibe_notification/core.py
vibe_notification/exceptions.py
vibe_notification/factories.py
vibe_notification/i18n.py
vibe_notification/input_utils.py
vibe_notification/managers.py
vibe_notification/models.py
vibe_notification/utils.py
vibe_notification/detectors/__init__.py
vibe_notification/detectors/conversation.py
vibe_notification/notifiers/__init__.py
vibe_notification/notifiers/base.py
vibe_notification/notifiers/sound.py
vibe_notification/notifiers/system.py
vibe_notification/parsers/__init__.py
vibe_notification/parsers/base.py
vibe_notification/parsers/claude_code.py
vibe_notification/parsers/codex.py
vibe_notification-1.0.4.dist-info/licenses/LICENSE
vibe_notification-1.0.4.dist-info/METADATA
vibe_notification-1.0.4.dist-info/WHEEL
vibe_notification-1.0.4.dist-info/entry_points.txt
vibe_notification-1.0.4.dist-info/top_level.txt
vibe_notification-1.0.4.dist-info/RECORD
