Metadata-Version: 2.4
Name: vibe-notification
Version: 1.0.4
Summary: 智能 AI 助手会话结束通知系统
Author-email: huangwb8 <hwb2012@qq.com>
License-Expression: MIT
Project-URL: Homepage, https://github.com/huangwb8/VibeNotification
Project-URL: Bug-Tracker, https://github.com/huangwb8/VibeNotification/issues
Project-URL: Documentation, https://github.com/huangwb8/VibeNotification#readme
Project-URL: Source, https://github.com/huangwb8/VibeNotification
Keywords: claude,codex,notification,ai,assistant
Classifier: Development Status :: 4 - Beta
Classifier: Intended Audience :: Developers
Classifier: Topic :: Software Development :: Libraries :: Python Modules
Classifier: Programming Language :: Python :: 3
Classifier: Programming Language :: Python :: 3.7
Classifier: Programming Language :: Python :: 3.8
Classifier: Programming Language :: Python :: 3.9
Classifier: Programming Language :: Python :: 3.10
Classifier: Programming Language :: Python :: 3.11
Classifier: Operating System :: OS Independent
Classifier: Operating System :: MacOS :: MacOS X
Classifier: Operating System :: Microsoft :: Windows
Classifier: Operating System :: POSIX :: Linux
Requires-Python: >=3.7
License-File: LICENSE
Dynamic: license-file
